dora_funasr/__init__.py
dora_funasr/__main__.py
dora_funasr/main.py
dora_funasr-0.0.0.dist-info/METADATA
dora_funasr-0.0.0.dist-info/WHEEL
dora_funasr-0.0.0.dist-info/entry_points.txt
dora_funasr-0.0.0.dist-info/top_level.txt
dora_funasr-0.0.0.dist-info/RECORD
