Metadata-Version: 2.4
Name: dora-funasr
Version: 0.0.0
Summary: dora-funasr
Author-email: Your Name <email@email.com>
License: MIT
Requires-Python: >=3.8
Requires-Dist: dora-rs>=0.3.9
Requires-Dist: funasr
Requires-Dist: torch>=2.5.1
Requires-Dist: torchaudio>=2.5.1
